umshini/__init__.py
umshini/example_client.py
umshini/learner.py
umshini/tournament_client.py
umshini/envs/__init__.py
umshini/envs/envs_list.py
umshini/examples/__init__.py
umshini/examples/connect_four.py
umshini/examples/example_agent.py
umshini/examples/example_cli.py
umshini/examples/local_game.py
umshini/utils/__init__.py
umshini/utils/compress.py
umshini/utils/socket_wrap.py
umshini/utils/test_compression.py
umshini/utils/validate_action.py
umshini-0.1.4.dist-info/LICENSE
umshini-0.1.4.dist-info/METADATA
umshini-0.1.4.dist-info/WHEEL
umshini-0.1.4.dist-info/top_level.txt
umshini-0.1.4.dist-info/RECORD
