Metadata-Version: 2.1
Name: umshini
Version: 0.1.4
Summary: Umshini client for playing in MARL tournaments
Author-email: "Jordan K. Terry" <j.k.terry@swarmlabs.com>, Elliot Tower <elliot.tower@swarmlabs.com>, Hannah Tan <hannah.tan@swarmlabs.com>
License: This code is copyright Jordan Terry, 2021, and is released under the GNU AGPLv3 license, included below:
Project-URL: Repository, https://github.com/Umshini/Umshini-Client/
Project-URL: Bug Report, https://github.com/Umshini/Umshini-Client/issues
Keywords: Reinforcement Learning,LLM,game,RL,AI,gymnasium,pettingzoo
Classifier: Development Status :: 4 - Beta
Classifier: Programming Language :: Python :: 3
Classifier: Programming Language :: Python :: 3.8
Classifier: Programming Language :: Python :: 3.9
Classifier: Programming Language :: Python :: 3.10
Classifier: Programming Language :: Python :: 3.11
Requires-Python: >=3.8
License-File: LICENSE
Requires-Dist: numpy >=1.19.0
Requires-Dist: pettingzoo >=1.24.0
Requires-Dist: gymnasium >=0.28.0
Requires-Dist: halo ==0.0.31
Requires-Dist: colorama ==0.4.6
Requires-Dist: chess ==1.9.4
Requires-Dist: rlcard ==1.0.5
Requires-Dist: pygame ==2.3.0
Requires-Dist: chatarena[umshini] >=0.1.17
Provides-Extra: testing
Requires-Dist: pytest ; extra == 'testing'
Requires-Dist: pytest-cov ; extra == 'testing'
Requires-Dist: deptry ; extra == 'testing'
